nsense_detection/__init__.py
nsense_detection/common/__init__.py
nsense_detection/common/common.py
nsense_detection/datasets/__init__.py
nsense_detection/datasets/coco_tools.py
nsense_detection/datasets/json_utils.py
nsense_detection/datasets/util.py
nsense_detection/lib/BoundingBox.py
nsense_detection/lib/BoundingBoxes.py
nsense_detection/lib/Evaluator.py
nsense_detection/lib/__init__.py
nsense_detection/lib/utils.py
nsense_detection/model/__init__.py
nsense_detection/model/load_model.py
nsense_detection/model/load_onnx.py
nsense_detection/model/load_trt.py
nsense_detection/model/load_vino.py
nsense_detection/models/__init__.py
nsense_detection/models/efficientdet/__init__.py
nsense_detection/models/efficientdet/efficientdet.py
nsense_detection/models/efficientdet/efficientdet_utils.py
nsense_detection/models/yolov7/__init__.py
nsense_detection/models/yolov7/yolov7.py
nsense_detection/models/yolov7/yolov7_utils.py
nsense_detection/models/yolox/__init__.py
nsense_detection/models/yolox/yolox.py
nsense_detection/models/yolox/yolox_utils.py
nsense_detection/utils/__init__.py
nsense_detection/utils/detector_utils.py
nsense_detection/utils/image_utils.py
nsense_detection/utils/nms_utils.py
nsense_detection/utils/util.py
nsense_detection-1.0.0.3.dist-info/METADATA
nsense_detection-1.0.0.3.dist-info/WHEEL
nsense_detection-1.0.0.3.dist-info/top_level.txt
nsense_detection-1.0.0.3.dist-info/RECORD
