Metadata-Version: 2.1
Name: nsense-detection
Version: 1.0.0.3
Summary: detection package
Home-page: https://github.com/nsense-ptas/deephuman
Author: gutaeu
Author-email: taewoo.g@nsensecorp.com
License: MIT
Platform: UNKNOWN
Requires-Python: >=3.6
Requires-Dist: numpy
Requires-Dist: opencv-python
Requires-Dist: torch (>=1.10)
Requires-Dist: openvino
Requires-Dist: onnxruntime-gpu
Requires-Dist: pycocotools
Requires-Dist: matplotlib
